CHANGELOG.md
LICENSE.txt
README.md
examples/README.md
qwstpad.py
qwstpad_micropython-0.0.1.dist-info/METADATA
qwstpad_micropython-0.0.1.dist-info/WHEEL
qwstpad_micropython-0.0.1.dist-info/licenses/LICENSE.txt
qwstpad_micropython-0.0.1.dist-info/RECORD
