Metadata-Version: 2.3
Name: qwstpad-micropython
Version: 0.0.1
Summary: Micropython library for the Pimoroni QwSTPad
Project-URL: GitHub, https://www.github.com/pimoroni/qwstpad-micropython
Project-URL: Homepage, https://www.pimoroni.com
Author-email: Chris P <chris@pimoroni.com>, Ryan H <ryan@pimoroni.com>
Maintainer-email: Chris P <chris@pimoroni.com>, Ryan H <ryan@pimoroni.com>
License-File: LICENSE.txt
Classifier: License :: OSI Approved :: MIT License
